CHANGELOG.rst
LICENSE
MANIFEST.in
README.rst
setup.cfg
setup.py
flask_restplus/__about__.py
flask_restplus/__init__.py
flask_restplus/_http.py
flask_restplus/api.py
flask_restplus/apidoc.py
flask_restplus/cors.py
flask_restplus/errors.py
flask_restplus/fields.py
flask_restplus/inputs.py
flask_restplus/marshalling.py
flask_restplus/mask.py
flask_restplus/model.py
flask_restplus/namespace.py
flask_restplus/postman.py
flask_restplus/representations.py
flask_restplus/reqparse.py
flask_restplus/resource.py
flask_restplus/swagger.py
flask_restplus/utils.py
flask_restplus/schemas/__init__.py
flask_restplus/schemas/oas-2.0.json
flask_restplus/templates/swagger-ui-css.html
flask_restplus/templates/swagger-ui-libs.html
flask_restplus/templates/swagger-ui.html
requirements/develop.pip
requirements/doc.pip
requirements/install.pip
requirements/test.pip
walmart_cloudsec_flask_restplus.egg-info/PKG-INFO
walmart_cloudsec_flask_restplus.egg-info/SOURCES.txt
walmart_cloudsec_flask_restplus.egg-info/dependency_links.txt
walmart_cloudsec_flask_restplus.egg-info/not-zip-safe
walmart_cloudsec_flask_restplus.egg-info/requires.txt
walmart_cloudsec_flask_restplus.egg-info/top_level.txt