Metadata-Version: 2.1
Name: walmart-cloudsec-flask-restplus
Version: 0.13.1.dev0
Summary: Fully featured framework for fast, easy and documented API development with Flask
Home-page: https://github.com/noirbizarre/flask-restplus
Author: Axel Haustant
Author-email: axel@data.gouv.fr
License: BSD-3-Clause
Keywords: flask restplus rest api swagger openapi
Platform: UNKNOWN
Classifier: Development Status :: 3 - Alpha
Classifier: Programming Language :: Python
Classifier: Environment :: Web Environment
Classifier: Operating System :: OS Independent
Classifier: Intended Audience :: Developers
Classifier: Topic :: System :: Software Distribution
Classifier: Programming Language :: Python
Classifier: Programming Language :: Python :: 2
Classifier: Programming Language :: Python :: 2.7
Classifier: Programming Language :: Python :: 3
Classifier: Programming Language :: Python :: 3.4
Classifier: Programming Language :: Python :: 3.5
Classifier: Programming Language :: Python :: 3.6
Classifier: Programming Language :: Python :: 3.7
Classifier: Programming Language :: Python :: Implementation :: PyPy
Classifier: Topic :: Software Development :: Libraries :: Python Modules
Classifier: License :: OSI Approved :: BSD License
Provides-Extra: doc
Provides-Extra: test
Provides-Extra: dev
